{"ticker": "YUM", "window_size": 4, "score": 0.6326, "training_F1": 0.4717, "training_precision": 0.5082, "training_recall": 0.5082, "test_F1": 0.7935, "test_precision": 0.8125, "test_recall": 0.8125, "target_length": 1, "target_theme": "s0005", "colname": ["normal_amplitude", "normal_volume", "normal_close", "normal_close_diff_day1", "normal_close_diff_day2", "normal_close_diff_day3", "normal_returns", "normal_mfi", "normal_weekday", "TXN_normal_amplitude", "TXN_normal_volume", "TXN_normal_close", "TXN_normal_close_diff_day1", "TXN_normal_close_diff_day2", "TXN_normal_close_diff_day3", "TXN_normal_returns", "TXN_normal_mfi"]}