{"ticker": "SYY", "window_size": 6, "score": 0.829, "training_F1": 0.8482, "training_precision": 0.8333, "training_recall": 0.8333, "test_F1": 0.8099, "test_precision": 0.8, "test_recall": 0.8, "target_length": 1, "target_theme": "s0005", "colname": ["normal_amplitude", "normal_volume", "normal_close", "normal_close_diff_day1", "normal_close_diff_day2", "normal_close_diff_day3", "normal_returns", "normal_mfi", "normal_weekday", "SRE_normal_amplitude", "SRE_normal_volume", "SRE_normal_close", "SRE_normal_close_diff_day1", "SRE_normal_close_diff_day2", "SRE_normal_close_diff_day3", "SRE_normal_returns", "SRE_normal_mfi"]}