{"ticker": "AES", "window_size": 4, "score": 0.3212, "training_F1": 0.3716, "training_precision": 0.4918, "training_recall": 0.4918, "test_F1": 0.2708, "test_precision": 0.375, "test_recall": 0.375, "target_length": 1, "target_theme": "s000", "colname": ["normal_amplitude", "normal_volume", "normal_close", "normal_close_diff_day1", "normal_close_diff_day2", "normal_close_diff_day3", "normal_returns", "normal_mfi", "normal_weekday", "NLSN_normal_amplitude", "NLSN_normal_volume", "NLSN_normal_close", "NLSN_normal_close_diff_day1", "NLSN_normal_close_diff_day2", "NLSN_normal_close_diff_day3", "NLSN_normal_returns", "NLSN_normal_mfi"]}