{"ticker": "AAPL", "score": 0.595, "test_loss": 0.6713, "test_acc": 0.625, "train_loss": 0.7014, "train_acc": 0.5677, "learn_rate": 0.0001, "dropout": 0.1, "epoch": 100, "window_size": 5, "target_length": 1, "target_theme": "g000", "colname": ["normal_amplitude", "normal_volume", "normal_close", "normal_close_diff_day1", "normal_close_diff_day2", "normal_close_diff_day3", "normal_returns", "normal_mfi", "normal_weekday", "DOV_normal_amplitude", "DOV_normal_volume", "DOV_normal_close", "DOV_normal_close_diff_day1", "DOV_normal_close_diff_day2", "DOV_normal_close_diff_day3", "DOV_normal_returns", "DOV_normal_mfi"]}