{"ticker": "AAPL", "score": 0.6009, "test_loss": 0.6594, "test_acc": 0.6327, "train_loss": 0.6885, "train_acc": 0.5722, "learn_rate": 0.0005, "dropout": 0.1, "epoch": 100, "window_size": 2, "target_length": 1, "target_theme": "g000", "colname": ["normal_amplitude", "normal_volume", "normal_close", "normal_close_diff_day1", "normal_close_diff_day2", "normal_close_diff_day3", "normal_returns", "normal_mfi", "normal_weekday", "CSX_normal_amplitude", "CSX_normal_volume", "CSX_normal_close", "CSX_normal_close_diff_day1", "CSX_normal_close_diff_day2", "CSX_normal_close_diff_day3", "CSX_normal_returns", "CSX_normal_mfi"]}