{"ticker": "VZ", "window_size": 4, "score": 0.5076, "training_F1": 0.3805, "training_precision": 0.4754, "training_recall": 0.4754, "test_F1": 0.6347, "test_precision": 0.6875, "test_recall": 0.6875, "target_length": 1, "target_theme": "s000", "colname": ["normal_amplitude", "normal_volume", "normal_close", "normal_close_diff_day1", "normal_close_diff_day2", "normal_close_diff_day3", "normal_returns", "normal_mfi", "normal_weekday", "TMO_normal_amplitude", "TMO_normal_volume", "TMO_normal_close", "TMO_normal_close_diff_day1", "TMO_normal_close_diff_day2", "TMO_normal_close_diff_day3", "TMO_normal_returns", "TMO_normal_mfi"]}