{"ticker": "VZ", "window_size": 7, "score": 0.5678, "training_F1": 0.5791, "training_precision": 0.5932, "training_recall": 0.5932, "test_F1": 0.5565, "test_precision": 0.5333, "test_recall": 0.5333, "target_length": 1, "target_theme": "g0005", "colname": ["normal_amplitude", "normal_volume", "normal_close", "normal_close_diff_day1", "normal_close_diff_day2", "normal_close_diff_day3", "normal_returns", "normal_mfi", "normal_weekday", "UAL_normal_amplitude", "UAL_normal_volume", "UAL_normal_close", "UAL_normal_close_diff_day1", "UAL_normal_close_diff_day2", "UAL_normal_close_diff_day3", "UAL_normal_returns", "UAL_normal_mfi"]}